ddcrelight/__about__.py
ddcrelight/__init__.py
ddcrelight/ddciface.py
ddcrelight/lightai.py
ddcrelight/lightsensor.py
ddcrelight/main.py
ddcrelight-0.0.1.dist-info/METADATA
ddcrelight-0.0.1.dist-info/WHEEL
ddcrelight-0.0.1.dist-info/entry_points.txt
ddcrelight-0.0.1.dist-info/licenses/LICENSE.txt
ddcrelight-0.0.1.dist-info/RECORD
