Metadata-Version: 2.1
Name: ddcrelight
Version: 0.0.1
Summary: Update monitor brightness intelligently using the DDC protocol.
Project-URL: Documentation, https://github.com/DarkArc/ddcrelight#readme
Project-URL: Issues, https://github.com/DarkArc/ddcrelight/issues
Project-URL: Source, https://github.com/DarkArc/ddcrelight
Author-email: Wyatt Childers <wchilders@nearce.com>
License-File: LICENSE.txt
Classifier: Development Status :: 4 - Beta
Classifier: Programming Language :: Python
Classifier: Programming Language :: Python :: 3.7
Classifier: Programming Language :: Python :: 3.8
Classifier: Programming Language :: Python :: 3.9
Classifier: Programming Language :: Python :: 3.10
Classifier: Programming Language :: Python :: Implementation :: CPython
Classifier: Programming Language :: Python :: Implementation :: PyPy
Requires-Python: >=3.7
Requires-Dist: yoctopuce
